CHANGES.rst
MANIFEST.in
README.rst
setup.cfg
setup.py
omnikassa/__init__.py
omnikassa/constants.py
omnikassa/exceptions.py
omnikassa/helpers.py
omnikassa/payment.py
omnikassa.egg-info/PKG-INFO
omnikassa.egg-info/SOURCES.txt
omnikassa.egg-info/dependency_links.txt
omnikassa.egg-info/not-zip-safe
omnikassa.egg-info/top_level.txt