Metadata-Version: 1.1
Name: omnikassa
Version: 0.0.4
Summary: Python library for implementing Omnikassa
Home-page: https://github.com/RobWouters/omnikassa
Author: Rob Wouters
Author-email: rob@rob-wouters.nl
License: UNKNOWN
Download-URL: https://github.com/RobWouters/omnikassa/tarball/0.0.4
Keywords: python omnikassa payment
Platform: UNKNOWN
Classifier: Programming Language :: Python
